sqlalchemy_db_graphing/__init__.py
sqlalchemy_db_graphing/constants.py
sqlalchemy_db_graphing/graph.py
sqlalchemy_db_graphing/style_presets.py
sqlalchemy_db_graphing-0.2.0.dist-info/LICENSE
sqlalchemy_db_graphing-0.2.0.dist-info/METADATA
sqlalchemy_db_graphing-0.2.0.dist-info/WHEEL
sqlalchemy_db_graphing-0.2.0.dist-info/top_level.txt
sqlalchemy_db_graphing-0.2.0.dist-info/RECORD
