Metadata-Version: 2.1
Name: sqlalchemy_db_graphing
Version: 0.2.0
Summary: A module to display sqlalchemy database tables and keys as a graph
Author-email: Erwan Nisol <erwan.nisol@free.fr>
Maintainer-email: Erwan Nisol <erwan.nisol@free.fr>
License: MIT license
Project-URL: bugs, https://github.com/erwann-met/sqlalchemy_db_graphing/issues
Project-URL: changelog, https://github.com/erwann-met/sqlalchemy_db_graphing/blob/master/changelog.md
Project-URL: homepage, https://github.com/erwann-met/sqlalchemy_db_graphing
License-File: LICENSE
Requires-Dist: sqlalchemy
Requires-Dist: pydot
Provides-Extra: dev
Requires-Dist: tox; extra == "dev"
Requires-Dist: coverage; extra == "dev"
Requires-Dist: mypy; extra == "dev"
Requires-Dist: pytest; extra == "dev"
Requires-Dist: ruff; extra == "dev"
Requires-Dist: black; extra == "dev"
